{
    "音檔長度": "9.81",
    "漢羅台文": "總--是，咱愛理解殖民霸權毋是一、兩冬的代誌，",
    "台羅": "tsóng--sī, lán ài lí-kái si̍t-bîn pà-khuân m̄ sī tsi̍t, nn̄g tang ê tāi-tsì,",
    "台羅數字調": "tsong2--si7,lan2 ai3 li2-kai2 sit8-bin5 pa3-khuan5 m7 si7 tsit8,nng7 tang1 e5 tai7-tsi3,",
    "白話字": "chóng--sī,lán ài lí-kái si̍t-bîn pà-khoân m̄ sī chi̍t,nn̄g tang ê tāi-chì,",
    "字數": "21",
    "提示卡編號": "0035",
    "句編號": "4.27",
    "發音人": "TSF0017",
    "性別": "女",
    "年齡": "53",
    "教育程度": "碩士",
    "出生地": "嘉義市",
    "現居地": "嘉義市",
    "腔調": "通行腔",
    "錄音環境": "安靜隔音室內",
    "提示卡切換速度": "慢",
    "總錄音時間(分)": "150"
}